.VERSION
AUTHORS.rst
CONTRIBUTING.rst
HISTORY.rst
LICENSE
MANIFEST.in
Pipfile
Pipfile.lock
README.rst
USAGE.rst
dev-requirements.txt
requirements.txt
setup.cfg
setup.py
docs/Makefile
docs/authors.rst
docs/conf.py
docs/contributing.rst
docs/history.rst
docs/index.rst
docs/installation.rst
docs/readme.rst
docs/usage.rst
ynabintegrationscli/.VERSION
ynabintegrationscli/AUTHORS.rst
ynabintegrationscli/CONTRIBUTING.rst
ynabintegrationscli/HISTORY.rst
ynabintegrationscli/LICENSE
ynabintegrationscli/Pipfile
ynabintegrationscli/Pipfile.lock
ynabintegrationscli/README.rst
ynabintegrationscli/USAGE.rst
ynabintegrationscli/__init__.py
ynabintegrationscli/_version.py
ynabintegrationscli/dev-requirements.txt
ynabintegrationscli/requirements.txt
ynabintegrationscli/ynabintegrationscli.py
ynabintegrationscli/ynabintegrationscliexceptions.py
ynabintegrationscli.egg-info/PKG-INFO
ynabintegrationscli.egg-info/SOURCES.txt
ynabintegrationscli.egg-info/dependency_links.txt
ynabintegrationscli.egg-info/entry_points.txt
ynabintegrationscli.egg-info/not-zip-safe
ynabintegrationscli.egg-info/requires.txt
ynabintegrationscli.egg-info/top_level.txt
ynabintegrationscli/conf/logging.json-example