Metadata-Version: 1.1
Name: ynabintegrationscli
Version: 0.1.0
Summary: A tool to  upload transactions from an abn amro account and credit card to ynab provided a configuration file and valid session cookies for an abn amro connection
Home-page: https://github.com/costastf/ynabintegrationscli
Author: Costas Tyfoxylos
Author-email: costas.tyf@gmail.com
License: MIT
Keywords: ynabintegrationscli
Platform: UNKNOWN
Classifier: Development Status :: 4 - Beta
Classifier: Intended Audience :: Developers
Classifier: License :: OSI Approved :: MIT License
Classifier: Natural Language :: English
Classifier: Programming Language :: Python :: 3.7
